{"body":{"name":"interior_mutability","params":[],"return_type":[49,"()"],"body_expr":37,"world_scope":48,"defs":{"data":[{"Expr":{"Path":{"Path":"RefCell::new"}}},{"Expr":{"Literal":"5"}},{"Expr":{"Call":{"callee":0,"args":[1]}}},{"Expr":{"Path":{"Binding":0}}},{"Expr":{"MethodCall":{"receiver":3,"fn_name":"borrow","args":[]}}},{"Expr":{"Path":{"Binding":0}}},{"Expr":{"MethodCall":{"receiver":5,"fn_name":"borrow_mut","args":[]}}},{"Expr":{"UnaryOp":{"expr":6,"op":"Deref"}}},{"Expr":{"Literal":"42"}},{"Expr":{"BinaryOp":{"lhs":7,"rhs":8,"op":{"Assignment":{"op":null}}}}},{"Expr":{"Path":{"Path":"std::io::_print"}}},{"Expr":{"Path":{"Binding":1}}},{"Expr":{"Literal":"\"\""}},{"Expr":{"Array":{"ElementList":{"elements":[12]}}}},{"Expr":{"Ref":{"expr":13,"mutability":"Shared"}}},{"Expr":{"Literal":"0"}},{"Expr":{"Literal":"' '"}},{"Expr":{"Path":{"Path":"Alignment::Unknown"}}},{"Expr":{"Literal":"0"}},{"Expr":{"Path":{"Path":"Count::Implied"}}},{"Expr":{"Path":{"Path":"Count::Implied"}}},{"Expr":{"Path":{"Path":"Placeholder::new"}}},{"Expr":{"Call":{"callee":21,"args":[15,16,17,18,19,20]}}},{"Expr":{"Array":{"ElementList":{"elements":[22]}}}},{"Expr":{"Ref":{"expr":23,"mutability":"Shared"}}},{"Expr":{"Ref":{"expr":11,"mutability":"Shared"}}},{"Expr":{"Path":{"Path":"Argument::new_display"}}},{"Expr":{"Call":{"callee":26,"args":[25]}}},{"Expr":{"Array":{"ElementList":{"elements":[27]}}}},{"Expr":{"Ref":{"expr":28,"mutability":"Shared"}}},{"Expr":{"Path":{"Path":"Arguments::new_v1_formatted"}}},{"Expr":{"Path":{"Path":"UnsafeArg::new"}}},{"Expr":{"Call":{"callee":31,"args":[]}}},{"Expr":{"Block":{"statements":[],"tail":32,"scope_start":40,"scope_end":41}}},{"Expr":{"Call":{"callee":30,"args":[14,29,24,33]}}},{"Expr":{"Call":{"callee":10,"args":[34]}}},{"Expr":{"Block":{"statements":[35],"tail":null,"scope_start":42,"scope_end":43}}},{"Expr":{"Block":{"statements":[45,46,9,36],"tail":null,"scope_start":44,"scope_end":47}}},{"Pat":{"Bind":{"annotation":null,"binding_id":0,"subpat":null}}},{"Pat":{"Bind":{"annotation":null,"binding_id":1,"subpat":null}}},"Noop","Noop","Noop","Noop","Noop",{"Expr":{"LetStatement":{"pat":38,"type_ref":null,"initializer":2}}},{"Expr":{"LetStatement":{"pat":39,"type_ref":null,"initializer":4}}},"Noop","Noop","Noop"]},"bindings":{"data":[{"Real":{"name":"ref_cell","marked_mutable":false}},{"Real":{"name":"shared_ref","marked_mutable":false}},"Fake"]},"next_def_map":[0,1,0,3,3,5,5,5,8,8,10,11,12,12,12,15,16,17,18,19,20,21,21,21,21,11,26,26,26,26,30,31,31,40,30,10,42,44,38,39,40,41,42,43,44,0,3,47,48,49],"never_defs":{"def_map":{"order":"bitvec::order::Lsb0","head":{"width":32,"index":0},"bits":50,"data":[0,0]}},"selectable_defs":{"def_map":{"order":"bitvec::order::Lsb0","head":{"width":32,"index":0},"bits":50,"data":[2088,208]}},"def_order":[3,4,5,8,9,12,13,14,11,15,17,23,19,20,21,29,30,31,32,33,34,28,35,36,37,24,22,25,26,27,18,39,40,42,43,44,46,48,2,7,38,41,16,45,1,6,10,47,0,49],"expr_resugaring":[null,null,null,null,null,null,null,null,null,null,null,null,null,null,null,null,null,null,null,null,null,null,null,null,null,null,null,null,null,null,null,null,null,null,null,null,{"Macro":{"call":"println!(\"{}\", shared_ref)","child_defs":[36,11]}}],"def_graph":[null,null,null,{"kind":"Usage","edges":[["Lifetime",39]],"active":{"def_map":{"order":"bitvec::order::Lsb0","head":{"width":32,"index":0},"bits":50,"data":[15,77888]}}},null,{"kind":"Usage","edges":[],"active":{"def_map":{"order":"bitvec::order::Lsb0","head":{"width":32,"index":0},"bits":50,"data":[319,94400]}}},null,null,null,null,null,{"kind":"Usage","edges":[],"active":{"def_map":{"order":"bitvec::order::Lsb0","head":{"width":32,"index":0},"bits":50,"data":[1140883455,95424]}}},null,null,null,null,null,null,null,null,null,null,null,null,null,null,null,null,null,null,null,null,null,null,null,null,null,null,{"kind":{"Source":{"binding":0,"mutable":false,"contains_lt":false,"scope":37}},"edges":[[{"Ref":{"mutability":false}},3],[{"Ref":{"mutability":false}},5]],"active":{"def_map":{"order":"bitvec::order::Lsb0","head":{"width":32,"index":0},"bits":50,"data":[4294967288,28639]}}},{"kind":{"Source":{"binding":1,"mutable":false,"contains_lt":true,"scope":37}},"edges":[[{"Ref":{"mutability":false}},11]],"active":{"def_map":{"order":"bitvec::order::Lsb0","head":{"width":32,"index":0},"bits":50,"data":[4294967264,184255]}}}],"def_graph_inv":[null,null,null,[38],null,[38],null,null,null,null,null,[39],null,null,null,null,null,null,null,null,null,null,null,null,null,null,null,null,null,null,null,null,null,null,null,null,null,null,null,[3]],"conflicts":[]},"selected":38}